gllm_plugin/__init__.pyi
gllm_plugin/config/__init__.pyi
gllm_plugin/config/app_config.pyi
gllm_plugin/config/constant.pyi
gllm_plugin/pipeline/__init__.pyi
gllm_plugin/pipeline/base_pipeline_preset_config.pyi
gllm_plugin/pipeline/pipeline_handler.pyi
gllm_plugin/pipeline/pipeline_plugin.pyi
gllm_plugin/storage/__init__.pyi
gllm_plugin/storage/base_anonymizer_storage.pyi
gllm_plugin/storage/base_chat_history_storage.pyi
gllm_plugin/supported_models.pyi
gllm_plugin/tools/__init__.pyi
gllm_plugin/tools/decorators.pyi
gllm_plugin.build/.gitignore
gllm_plugin.cpython-311-x86_64-linux-gnu.so
gllm_plugin.pyi
gllm_plugin-0.0.5.dist-info/METADATA
gllm_plugin-0.0.5.dist-info/WHEEL
gllm_plugin-0.0.5.dist-info/RECORD
