Metadata-Version: 2.1
Name: gllm-plugin
Version: 0.0.5
Summary: 
Author: GenAI SDK Team
Author-email: gat-sdk@gdplabs.id
Requires-Python: >=3.11,<3.13
Classifier: Programming Language :: Python :: 3
Classifier: Programming Language :: Python :: 3.11
Classifier: Programming Language :: Python :: 3.12
Provides-Extra: flair
Requires-Dist: bosa-core
Requires-Dist: gllm-core
Requires-Dist: gllm-inference
Requires-Dist: gllm-pipeline
Requires-Dist: langchain (>=0.3.0,<0.4.0)
Requires-Dist: langchain-core (>=0.3.51)
Requires-Dist: semver (>=3.0.4,<4.0.0)
